LICENSE
MANIFEST.in
README.md
pyproject.toml
setup.py
ctc_segmentation/__init__.py
ctc_segmentation/ctc_segmentation.py
ctc_segmentation/ctc_segmentation_dyn.c
ctc_segmentation/ctc_segmentation_dyn.pyx
ctc_segmentation/partitioning.py
ctc_segmentation.egg-info/PKG-INFO
ctc_segmentation.egg-info/SOURCES.txt
ctc_segmentation.egg-info/dependency_links.txt
ctc_segmentation.egg-info/not-zip-safe
ctc_segmentation.egg-info/requires.txt
ctc_segmentation.egg-info/top_level.txt