Metadata-Version: 2.1
Name: ctc-segmentation
Version: 1.7.3
Summary: CTC segmentation to align utterances within large audio files.
Home-page: https://github.com/lumaku/ctc-segmentation
Author: Ludwig Kuerzinger <ludwig.kuerzinger@tum.de>, Dominik Winkelbauer <dominik.winkelbauer@tum.de>
License: UNKNOWN
Platform: UNKNOWN
Requires-Python: >=3.6
License-File: LICENSE
